{
  "model_overview": {
    "모델_유형": "Random Parameter Logit (RPL)",
    "이론적_기반": "McFadden의 확률효용이론 + 개인 이질성",
    "핵심_특징": [
      "개인별로 다른 선호 계수 (β_i ~ f(β, Σ))",
      "SEM 요인이 계수 분포에 영향",
      "IIA(Independence of Irrelevant Alternatives) 가정 완화",
      "개인 이질성의 명시적 모델링"
    ],
    "효용함수_구조": "\n        U_nit = β_i1·Sugar_nt + β_i2·HealthLabel_nt + β_i3·Price_nt + \n                β_i4·(Sugar×HealthLabel)_nt + β_i5·PerceivedBenefit_n + \n                β_i6·NutritionKnowledge_n + β_i7·PerceivedPrice_n + \n                β_i8·HealthConcern_n + ε_nit\n        \n        여기서 β_i = β + Γ·Z_i + σ·v_i\n        - β: 평균 계수 벡터\n        - Γ: SEM 요인 효과 행렬  \n        - Z_i: 개인 i의 SEM 요인 점수\n        - σ: 계수 표준편차\n        - v_i: 개인별 확률 성분\n        ",
    "기존_모델과의_차이": {
      "고정_계수_모델": "모든 개인이 동일한 β 사용",
      "RPL_모델": "개인별 β_i 사용, SEM 요인이 β_i 분포에 영향"
    }
  },
  "policy_implications": {
    "세분화_전략": [
      "건강 의식 높은 그룹: 무설탕 + 건강라벨 조합 제품 집중 마케팅",
      "영양 지식 풍부한 그룹: 건강라벨의 구체적 정보 강조",
      "가격 민감 그룹: 가격 대비 건강 혜택 강조",
      "일반 소비자: 기본적인 건강 정보 제공"
    ],
    "제품_개발": [
      "무설탕 제품에 명확한 건강라벨 부착 필수",
      "건강 혜택을 구체적으로 설명하는 패키징",
      "가격 대비 건강 가치 명시",
      "소비자 교육을 통한 영양 지식 향상"
    ],
    "마케팅_커뮤니케이션": [
      "개인별 맞춤형 메시지 전략",
      "건강 관심도에 따른 차별화된 광고",
      "영양 지식 수준별 정보 제공",
      "가격 민감도를 고려한 프로모션"
    ],
    "정책_제안": [
      "설탕 대체재 사용 제품에 대한 명확한 라벨링 기준",
      "소비자 영양 교육 프로그램 강화",
      "건강 기능성 표시 기준 개선",
      "가격 정책을 통한 건강한 선택 유도"
    ]
  },
  "limitations_and_future": {
    "현재_연구의_한계": [
      "시뮬레이션 기반 분석으로 실제 추정 결과와 차이 가능",
      "SEM 요인의 계수 영향이 선형적으로만 모델링됨",
      "시간에 따른 선호 변화 미반영",
      "상황적 요인(구매 맥락) 고려 부족"
    ],
    "향후_연구_방향": [
      "실제 데이터를 활용한 베이지안 추정",
      "비선형 SEM 효과 모델링",
      "동적 RPL 모델 개발 (시간 변화 반영)",
      "상황별 선택 모델 통합",
      "머신러닝 기법과의 결합"
    ],
    "방법론_개선": [
      "Mixed Logit과 Latent Class Model 결합",
      "계층적 베이지안 모델 적용",
      "개인별 학습 효과 반영",
      "다중 선택 상황 동시 모델링"
    ]
  }
}